{"html_attributions":[],"result":{"formatted_phone_number":"020 8859 1110","geometry":{"location":{"lat":51.45145869999999,"lng":0.05764499999999999},"viewport":{"northeast":{"lat":51.45273823029149,"lng":0.05875358029150202},"southwest":{"lat":51.4500402697085,"lng":0.05605561970849796}}},"name":"Eltham Children's Centre","opening_hours":{"open_now":false,"periods":[{"close":{"day":1,"time":"1500"},"open":{"day":1,"time":"1330"}},{"close":{"day":2,"time":"1500"},"open":{"day":2,"time":"1330"}},{"close":{"day":3,"time":"1500"},"open":{"day":3,"time":"1330"}},{"close":{"day":4,"time":"1500"},"open":{"day":4,"time":"1000"}},{"close":{"day":5,"time":"1630"},"open":{"day":5,"time":"0930"}}],"weekday_text":["Monday: 1:30 – 3:00 PM","Tuesday: 1:30 – 3:00 PM","Wednesday: 1:30 – 3:00 PM","Thursday: 10:00 AM – 3:00 PM","Friday: 9:30 AM – 4:30 PM","Saturday: Closed","Sunday: Closed"]},"photos":[{"height":2000,"html_attributions":["<a href=\"https://maps.google.com/maps/contrib/100823117664821074407\">Eltham Children&#39;s Centre</a>"],"photo_reference":"AWU5eFiEk5Ms8nUXuNMTH0V6LQsl2R3OzFk7UEWm_3p5vVl_BSvkNpjo3WT4u_Dlm4l5faoAooMbCNxtp553jaI_KXTb9x-712njyQBnbOY1L93piqtIvtqVoikv8m9-8hJiBrrY0cGSQf7sa3JE3BmAM4YyARAQFf54potOpTs6WYohoX40","width":924},{"height":924,"html_attributions":["<a href=\"https://maps.google.com/maps/contrib/100823117664821074407\">Eltham Children&#39;s Centre</a>"],"photo_reference":"AWU5eFiooVqOwG3bZWKA9BZPC3pLlJ2_xFmKpry6bVbHLHXFza0cNgYuKYx8NGln-VEBLlpvv5bU_MPk1LpKugIe82TkTXppt7mOKouOb0WFhZe0kJzsnWXrA1xlsVgYwNS20oY7Sg2iFmVm4lkbg-RtnTws-A01aXgDzX1vOtHTBMbUXUkd","width":2000},{"height":2000,"html_attributions":["<a href=\"https://maps.google.com/maps/contrib/100823117664821074407\">Eltham Children&#39;s Centre</a>"],"photo_reference":"AWU5eFj9tmJN10itoomSGZGHC-tHaETsNGFJ8TN1MtPxCYyaZhTV24n_DXuJkL4iTihixhg95TQmExLNinlZVkuDq0LanNv4ZW0v79Jgs-1l9XyLFFJ5vGhpU4piJcRIpzmQGL4YVQWocxve8neVKFnHLr9-N4c2sji-yCnveKQh2HGtbhD7","width":924}],"rating":5,"reviews":[{"author_name":"Nashrin McConville","author_url":"https://www.google.com/maps/contrib/106203776270828141641/reviews","language":"en","original_language":"en","profile_photo_url":"https://lh3.googleusercontent.com/a/ACg8ocJ8702xB3w7jksmA5LrkLz_8rMzW_kYKyIjtPKrX_aJ=s128-c0x00000000-cc-rp-mo","rating":5,"relative_time_description":"3 weeks ago","text":"Great Stay & Play session. Very friendly and supportive staff!","time":1699460508,"translated":false}],"user_ratings_total":1,"website":"https://www.better.org.uk/children-centre/london/greenwich/eltham-childrens-centre?utm_source=google&utm_medium=organic&utm_campaign=google_my_business"},"status":"OK","place_id":"ChIJlYGFsHKp2EcRGZu69ok-xLo","address":"The Eltham Centre, 2 Archery Rd, London SE9 1HA, United Kingdom","categories":["stay and play"]}