{"html_attributions":[],"result":{"geometry":{"location":{"lat":51.59355069999999,"lng":-0.0877969},"viewport":{"northeast":{"lat":51.59489968029149,"lng":-0.08644791970849797},"southwest":{"lat":51.59220171970849,"lng":-0.08914588029150204}}},"name":"Lordship Recreation Ground Paddling Pool","photos":[{"height":2736,"html_attributions":["<a href=\"https://maps.google.com/maps/contrib/115605009980605464699\">melissa</a>"],"photo_reference":"AWU5eFiA3yEFtyy_7SxeZQ_4H51O1MPNrlZwGuyqZDfneUFXXaXxzks4UhABOrIphA67xQqfT7wfcoUYCGgoYZxz8Nk6Co162h9eTn8Xy7EaVgR7PzpFyLRPgUoKSX1eqSm6-uur91hqDXfIDcLB6qZCEPV-cMAYE9uynmrBIDFXlHFueWSW","width":3648},{"height":2268,"html_attributions":["<a href=\"https://maps.google.com/maps/contrib/113653532138872885501\">Richard Drew</a>"],"photo_reference":"AWU5eFigwDlGrPA9ucOo_KQICfA_7xjBuPp9K_5ElKLHAo2ZVVIoQyJvPYWDaFU6cewtRMolyWwfJhzbHhhc3m1Pqys5Vrv2jfYdtnma7ALBwKitmt8Co_HTJzawGPrnv-J4wUgSaRbUsjhDHQ8SpL3Mcj4TJo1DEqPS1C3XOcrlgrxlslG7","width":4032}],"rating":4,"reviews":[{"author_name":"Richard Drew","author_url":"https://www.google.com/maps/contrib/113653532138872885501/reviews","language":"en","original_language":"en","profile_photo_url":"https://lh3.googleusercontent.com/a-/ALV-UjXkWGVL-r6TAvqB1y5Lyb0mC3wWj1yDmaTaQNXFXE5GAZhF=s128-c0x00000000-cc-rp-mo-ba5","rating":4,"relative_time_description":"5 months ago","text":"Just been filled for the summer\nNew access ramp installed","time":1686562777,"translated":false},{"author_name":"PR 21Century","author_url":"https://www.google.com/maps/contrib/104516449245151075813/reviews","language":"en","original_language":"en","profile_photo_url":"https://lh3.googleusercontent.com/a/ACg8ocJu0xB6lgIMxOtg7ae7tk5KNhSzcEUMCMpH_s0q0b6P=s128-c0x00000000-cc-rp-mo","rating":4,"relative_time_description":"2 years ago","text":"Water seems clean enough and they change it often. Must watch our for occasional weird people out there.","time":1627324231,"translated":false},{"author_name":"Arvin Shokri","author_url":"https://www.google.com/maps/contrib/102113717912236606849/reviews","language":"en","original_language":"en","profile_photo_url":"https://lh3.googleusercontent.com/a-/ALV-UjWIDErVYBnska1t9Q21RtjAm3h3M-Hr9ccLLcC9gs2wew=s128-c0x00000000-cc-rp-mo","rating":5,"relative_time_description":"3 months ago","text":"Beautifully shop😍","time":1693315465,"translated":false},{"author_name":"Craigton Pollock","author_url":"https://www.google.com/maps/contrib/109398827622506351056/reviews","language":"en","original_language":"en","profile_photo_url":"https://lh3.googleusercontent.com/a/ACg8ocKElXrkQ5t3YM5d_mrEKYDRx_YahjrwNuUOrMGTREnE=s128-c0x00000000-cc-rp-mo","rating":4,"relative_time_description":"2 years ago","text":"Nice place to take your children for play time","time":1628175578,"translated":false},{"author_name":"James Brown","author_url":"https://www.google.com/maps/contrib/112963198597898105474/reviews","profile_photo_url":"https://lh3.googleusercontent.com/a-/ALV-UjU1wiRy6hEBN8QrsNJIN68adV_cJKQroP03BhJhxjM9ErQ=s128-c0x00000000-cc-rp-mo-ba5","rating":5,"relative_time_description":"2 years ago","text":"","time":1628781411,"translated":false}],"user_ratings_total":7,"website":"https://lordshiprec.org.uk/what-to-see-do/young-childrens-playground/"},"status":"OK","place_id":"ChIJxYFOaDAddkgRz4Ro2fQnNDA","address":"London N17 6NU, United Kingdom","categories":["water play"]}